qat/plugins/hook_synthopline.so
qat/synthopline/__init__.so
qat/synthopline/aa_pauli_synth.so
qat/synthopline/clifford_conjugation_tables.so
qat/synthopline/clifford_normalizer.so
qat/synthopline/co_diagonalization.so
qat/synthopline/compiler.so
qat/synthopline/gates.so
qat/synthopline/initial_mapping.so
qat/synthopline/interface.so
qat/synthopline/interface_wrapper.so
qat/synthopline/lazy.so
qat/synthopline/lazy_ions.so
qat/synthopline/libqatsynthopline.so
qat/synthopline/libstim.so
qat/synthopline/linear_synthesis.so
qat/synthopline/pauli_synth.so
qat/synthopline/phase_polynomials.so
qat/synthopline/sabre_clifford.so
qat/synthopline/util.so
qat/synthopline/version.so
qat_synthopline-0.5.0.dist-info/licenses/LICENSE.txt
qat_synthopline-0.5.0.dist-info/METADATA
qat_synthopline-0.5.0.dist-info/WHEEL
qat_synthopline-0.5.0.dist-info/top_level.txt
qat_synthopline-0.5.0.dist-info/RECORD
