Metadata-Version: 2.4
Name: qat-synthopline
Version: 0.5.0
Summary: Module qat-synthopline [c09dbac] - Compiled by Eviden
Home-page: https://atos.net/en/lp/myqlm
Author: Eviden Quantum Lab
Author-email: myqlm@atos.net
License: Eviden myQLM EULA
Project-URL: Documentation, https://myqlm.github.io
Project-URL: Bug Tracker, https://github.com/myQLM/myqlm-issues/issues
Project-URL: Community, https://myqlmworkspace.slack.com
Keywords: Quantum,myQLM,QLM,Atos,Eviden
Platform: Operating System :: Microsoft :: Windows
Classifier: Operating System :: Microsoft :: Windows
Classifier: Programming Language :: Python :: 3.1
Classifier: Topic :: Scientific/Engineering
Classifier: License :: Other/Proprietary License
License-File: LICENSE.txt
Requires-Dist: networkx
Requires-Dist: numpy
Requires-Dist: stim
Requires-Dist: rich
Requires-Dist: qat-comm
Requires-Dist: qat-core
Requires-Dist: qat-devices
Requires-Dist: qat-lang
Requires-Dist: qat-nnize
Requires-Dist: qat-pbo
Dynamic: author
Dynamic: author-email
Dynamic: classifier
Dynamic: description
Dynamic: description-content-type
Dynamic: home-page
Dynamic: keywords
Dynamic: license
Dynamic: license-file
Dynamic: platform
Dynamic: project-url
Dynamic: requires-dist
Dynamic: summary
